supergraph/__init__.py
supergraph/compiler/__init__.py
supergraph/compiler/artificial.py
supergraph/compiler/base.py
supergraph/compiler/graph.py
supergraph/compiler/jax_utils.py
supergraph/compiler/node.py
supergraph/compiler/partition_runner.py
supergraph/compiler/pendulum/__init__.py
supergraph/compiler/pendulum/nodes.py
supergraph/compiler/requirements.txt
supergraph/compiler/utils.py
supergraph/deprecated.py
supergraph/evaluate.py
supergraph/open_colors.py
supergraph/paper.py
supergraph-0.0.8.dist-info/LICENSE
supergraph-0.0.8.dist-info/METADATA
supergraph-0.0.8.dist-info/WHEEL
supergraph-0.0.8.dist-info/RECORD
